{"cameraMode":{"drawMode":0,"name":"Shaded","section":"Shading Mode"},"sceneLighting":true,"audioPlay":false,"sceneViewState":{"showFog":true,"showMaterialUpdate":false,"showSkybox":true,"showFlares":true,"showImageEffects":true,"showParticleSystems":true},"in2DMode":false,"pivot":{"x":6.147339820861816,"y":-2.5347633361816408,"z":54.242271423339847},"rotation":{"x":0.18635918200016023,"y":-0.021513119339942933,"z":0.004073626361787319,"w":0.982248067855835},"size":104.03587341308594,"orthographic":false}